Metadata-Version: 2.1
Name: calcDiameter
Version: 0.15
Summary: The program takes in a Molecular Assembly PDB file as arument, finds the right orientation such that the ring sits on the XY plane, projects all atoms onto the XY plane and calculates the max diameter between two atoms that lie furthest apart on the XY plane
Home-page: UNKNOWN
Author: Jan Zaucha
Author-email: j.zaucha@tum.de
License: MIT
Platform: UNKNOWN
